{"EDITOR_STATE":{"allProjectFiles":{"7af8b8ee-6e79-4aff-9389-1c6f522f970b":{"id":"7af8b8ee-6e79-4aff-9389-1c6f522f970b","parent":null,"name":"Hiru_RDS","type":"DIRECTORY","isDirectory":true,"children":["27d60cf3-6933-4160-ace9-429ab75e6c05","b4a138ae-ac81-499d-bf5b-4a0c285eea93","ca2af237-4340-4804-a5e8-85f8d124fc6e","bb8fc1d1-ef0b-4bc2-a65a-4a4bf67cce12","c3d072e8-3ade-46ac-8076-26410b22d714","b8b819f2-0c2d-4557-b2bf-3d59ba04027f"],"isRemovable":false,"filePath":"Hiru_RDS"},"27d60cf3-6933-4160-ace9-429ab75e6c05":{"id":"27d60cf3-6933-4160-ace9-429ab75e6c05","parent":"7af8b8ee-6e79-4aff-9389-1c6f522f970b","name":"lambda.js","type":"LAMBDA_FILE","isDirectory":false,"children":[],"isRemovable":true,"filePath":"Hiru_RDS/lambda.js","code":"let AWS = require('aws-sdk');\nconst s3 = new AWS.S3();\nexports.handler = function (event, context, callback) {\n\n\ts3.deleteObject({\n\t\t'Bucket': \"hiru.demo01\",\n\t\t'Key': \"test\"\n\t}).promise()\n\t\t.then(data => {\n\t\t\tconsole.log(data);           // successful response\n\t\t\t/*\n\t\t\t\tdata = {}\n\t\t\t*/\n\t\t})\n\t\t.catch(err => {\n\t\t\tconsole.log(err, err.stack); // an error occurred\n\t\t});\n\n\ts3.listObjects({\n\t\t'Bucket': 'hiru.demo01',\n\t\t'MaxKeys': 10,\n\t\t'Prefix': 'test'\n\t}).promise()\n\t\t.then(data => {\n\t\t\tconsole.log(data);           // successful response\n\t\t\t/*\n\t\t\tdata = {\n\t\t\t Contents: [\n\t\t\t\t{\n\t\t\t\t   ETag: \"\\\\\"70ee1738b6b21e2c8a43f3a5ab0eee71\\\\\"\",\n\t\t\t\t   Key: \"example1.jpg\",\n\t\t\t\t   LastModified: <Date Representation>,\n\t\t\t\t   Owner: {\n\t\t\t\t\t  DisplayName: \"myname\",\n\t\t\t\t\t  ID: \"12345example25102679df27bb0ae12b3f85be6f290b936c4393484be31bebcc\"\n\t\t\t\t   },\n\t\t\t\t   Size: 11,\n\t\t\t\t   StorageClass: \"STANDARD\"\n\t\t\t\t},\n\t\t\t\t{...}\n\t\t\t*/\n\t\t})\n\t\t.catch(err => {\n\t\t\tconsole.log(err, err.stack); // an error occurred\n\t\t});\n\n\n\n\tcallback(null, 'Successfully executed');\n}","resources":["rds-HiruID","s3hirusample","s3hirusample","s3hirusampledemo01","apigusEast1APIANYUdataput","s3hirusampledemo01","s3hirusampledemo01","s3hirudemo01","s3hirudemo01"],"triggers":[{"resourceName":"apigusEast1APIANYUdataput","config":{}}],"version":1},"b4a138ae-ac81-499d-bf5b-4a0c285eea93":{"id":"b4a138ae-ac81-499d-bf5b-4a0c285eea93","parent":"7af8b8ee-6e79-4aff-9389-1c6f522f970b","name":"test.js","type":"LAMBDA_FILE","isDirectory":false,"children":[],"isRemovable":true,"filePath":"Hiru_RDS/test.js","code":"let AWS = require('aws-sdk');\nconst sns = new AWS.SNS();\nconst s3 = new AWS.S3();\nexports.handler = function (event, context, callback) {\n\ts3.getObject({\n\t\t'Bucket': \"hiru.demo01\",\n\t\t'Key': \"test\"\n\t}).promise()\n\t\t.then(data => {\n\t\t\tconsole.log(data);           // successful response\n\t\t\t\n\t\t})\n\t\t.catch(err => {\n\t\t\tconsole.log(err, err.stack); // an error occurred\n\t\t});\n\tsns.getTopicAttributes({\n\t\tTopicArn: 'arn:aws:sns:us-east-1:263248768798:hiru'\n\t}).promise()\n\t\t.then(data => {\n\t\t\tconsole.log(data); // your code goes here\n\t\t})\n\t\t.catch(err => {\n\t\t\tconsole.log(err, err.stack); // error handling goes here\n\t\t});\n\n\n\n\n\tcallback(null, 'Successfully executed');\n}","resources":["s3hirusampledemo01","apigusEast1APIANYUdataget","s3hirusample","snsusEast1hiru","s3hirudemo01","s3hirudemo01"],"triggers":[{"resourceName":"apigusEast1APIANYUdataget","config":{}}],"version":1},"ca2af237-4340-4804-a5e8-85f8d124fc6e":{"id":"ca2af237-4340-4804-a5e8-85f8d124fc6e","parent":"7af8b8ee-6e79-4aff-9389-1c6f522f970b","name":"s3test.js","type":"LAMBDA_FILE","isDirectory":false,"children":[],"isRemovable":true,"filePath":"Hiru_RDS/s3test.js","code":"let AWS = require('aws-sdk');\nconst sns = new AWS.SNS();\nexports.handler = function (event, context, callback) {\n\t\n\tsns.getTopicAttributes({\n\t\tTopicArn: 'arn:aws:sns:us-east-1:263248768798:hiru'\n\t}).promise()\n\t\t.then(data => {\n\t\t\t// your code goes here\n\t\t})\n\t\t.catch(err => {\n\t\t\t// error handling goes here\n\t\t});\n\n\n\tcallback(null, 'Successfully executed');\n}","resources":["s3hirudemo01","snsusEast1hiru","snsusEast1hiru"],"triggers":[{"resourceName":"s3hirudemo01","config":{"type":"s3:ObjectCreated:*","keyPrefix":"sample","keySuffix":".jpg"}}],"version":1},"bb8fc1d1-ef0b-4bc2-a65a-4a4bf67cce12":{"id":"bb8fc1d1-ef0b-4bc2-a65a-4a4bf67cce12","parent":"7af8b8ee-6e79-4aff-9389-1c6f522f970b","name":"test123.js","type":"LAMBDA_FILE","isDirectory":false,"children":[],"isRemovable":true,"filePath":"Hiru_RDS/test123.js","code":"let AWS = require('aws-sdk');\nexports.handler = function(event, context, callback) {\n\n\n\tcallback(null,'Successfully executed');\n}","resources":[],"triggers":[]},"c3d072e8-3ade-46ac-8076-26410b22d714":{"id":"c3d072e8-3ade-46ac-8076-26410b22d714","parent":"7af8b8ee-6e79-4aff-9389-1c6f522f970b","name":"no commit.js","type":"LAMBDA_FILE","isDirectory":false,"children":[],"isRemovable":true,"filePath":"Hiru_RDS/no commit.js","code":"let AWS = require('aws-sdk');\nexports.handler = function(event, context, callback) {\n\n\n\tcallback(null,'Successfully executed');\n}","resources":[],"triggers":[]},"b8b819f2-0c2d-4557-b2bf-3d59ba04027f":{"id":"b8b819f2-0c2d-4557-b2bf-3d59ba04027f","parent":"7af8b8ee-6e79-4aff-9389-1c6f522f970b","name":"test11.js","type":"LAMBDA_FILE","isDirectory":false,"children":[],"isRemovable":true,"filePath":"Hiru_RDS/test11.js","code":"let AWS = require('aws-sdk');\nexports.handler = function(event, context, callback) {\n\n\n\tcallback(null,'Successfully executed');\n}","resources":[],"triggers":[]}},"rootNode":"7af8b8ee-6e79-4aff-9389-1c6f522f970b","openFiles":["27d60cf3-6933-4160-ace9-429ab75e6c05","b4a138ae-ac81-499d-bf5b-4a0c285eea93","ca2af237-4340-4804-a5e8-85f8d124fc6e"],"currentFileId":"ca2af237-4340-4804-a5e8-85f8d124fc6e","resources":{"apigusEast1APIANYUdataget":{"name":"apigusEast1APIANYUdataget","type":"API_GATEWAY","config":{"selectedRegion":"us-east-1","apiMode":0,"apiName":"API_ANYU","apiId":"x2a9drkc77","endpointType":"EDGE","rootResourceId":"dpk6r7zz9k","existingResources":{"/":"dpk6r7zz9k","/data":"resewg"},"resourceMode":0,"resourcePath":"/data","resourceName":"data","resourceId":"resewg","restMethod":"GET","proxyIntegration":false,"enableCORS":false,"stageMode":0,"stageName":"Prod","stageDeploymentId":"54wgax"},"globallyEditable":true,"usage":{"b4a138ae-ac81-499d-bf5b-4a0c285eea93":{"operations":{},"occurrence":1,"triggers":[{}]}}},"apigusEast1APIANYUdataput":{"name":"apigusEast1APIANYUdataput","type":"API_GATEWAY","config":{"selectedRegion":"us-east-1","apiMode":0,"apiName":"API_ANYU","endpointType":"EDGE","resourceMode":0,"resourceName":"data","resourcePath":"/data","restMethod":"PUT","proxyIntegration":false,"enableCORS":false,"stageMode":0,"stageName":"Prod"},"globallyEditable":true,"usage":{"27d60cf3-6933-4160-ace9-429ab75e6c05":{"operations":{},"occurrence":1,"triggers":[{}]}}},"snsusEast1hiru":{"name":"snsusEast1hiru","type":"SNS","config":{"topicMode":0,"topicName":"hiru","topicArn":"arn:aws:sns:us-east-1:263248768798:hiru","topicRegion":"us-east-1","snsType":0,"subscriptions":[{"type":"email","endpoint":"hirudineel@gmail.com"}]},"globallyEditable":true,"usage":{"b4a138ae-ac81-499d-bf5b-4a0c285eea93":{"operations":{"getTopicAttributes":[{"TopicArn":"arn:aws:sns:us-east-1:263248768798:hiru"}]},"occurrence":1,"triggers":[]},"ca2af237-4340-4804-a5e8-85f8d124fc6e":{"operations":{"getTopicAttributes":[{"TopicArn":"arn:aws:sns:us-east-1:263248768798:hiru"}]},"occurrence":1,"triggers":[]}}},"s3hirudemo01":{"name":"s3hirudemo01","type":"S3","config":{"mode":0,"bucket":{"region":"us-east-1","name":"hiru.demo01"}},"globallyEditable":false,"usage":{"27d60cf3-6933-4160-ace9-429ab75e6c05":{"operations":{"deleteObject":[{"Bucket":"hiru.demo01","Key":"test"}],"listObjects":[{"Bucket":"hiru.demo01","MaxKeys":10,"Prefix":"test"}]},"occurrence":2,"triggers":[]},"b4a138ae-ac81-499d-bf5b-4a0c285eea93":{"operations":{"getObject":[{"Bucket":"hiru.demo01","Key":"test"}]},"occurrence":1,"triggers":[]},"ca2af237-4340-4804-a5e8-85f8d124fc6e":{"operations":{},"occurrence":1,"triggers":[{"type":"s3:ObjectCreated:*","keyPrefix":"sample","keySuffix":".jpg"}]}}}},"packageJSON":{"dependencies":{"aws-sdk":{"name":"aws-sdk","version":"2.176.0","notRemovable":true},"slappforge-sdk":{"name":"@slappforge/slappforge-sdk","version":"0.0.3","notRemovable":true,"types":"\n                    declare class RDSQueryParams {\n    instanceIdentifier: string;\n    query: string;\n    inserts: Array<any>\n}\n\ndeclare namespace SL.AWS {\n    class RDS {\n        query(params: RDSQueryParams, callback: Function, connection: any): void;\n\n        beginTransaction(params: any, callback: Function): void;\n    }\n\n    class SQS {\n        receiveAndDeleteMessages(params: any, filteringCallBack: Function, deleteCallBack: Function, errorCallBack: Function): void;\n    }\n}\n"}}},"lambdaId":"27d60cf3-6933-4160-ace9-429ab75e6c05","changeExistingProject":false,"additionalFiles":[]},"PROJECT_META":{"projectName":"Hiru_RDS","projectDescription":"","projectVersion":"0.6.0","projectRegion":"us-east-1","repoName":"Hiru_RDS","repoUrl":"https://github.com/hirudinee/Hiru_RDS","lastSave":1518429921604}}